netml/__init__.py
netml/cli.py
netml/ndm/__init__.py
netml/ndm/ae.py
netml/ndm/gmm.py
netml/ndm/iforest.py
netml/ndm/kde.py
netml/ndm/model.py
netml/ndm/ocsvm.py
netml/ndm/pca.py
netml/pparser/__init__.py
netml/pparser/parser.py
netml/utils/__init__.py
netml/utils/tool.py
netml/visual/__init__.py
netml-0.7.1.dist-info/LICENSE
netml-0.7.1.dist-info/METADATA
netml-0.7.1.dist-info/WHEEL
netml-0.7.1.dist-info/entry_points.txt
netml-0.7.1.dist-info/top_level.txt
netml-0.7.1.dist-info/RECORD
