Metadata-Version: 2.1
Name: netml
Version: 0.7.1
Summary: Feature Extraction and Machine Learning from Network Traffic Traces
Home-page: https://github.com/noise-lab/netml
License: Apache 2.0
Classifier: Development Status :: 2 - Pre-Alpha
Classifier: Intended Audience :: Developers
Classifier: Intended Audience :: Education
Classifier: Intended Audience :: Science/Research
Classifier: License :: OSI Approved :: Apache Software License
Classifier: Programming Language :: Python :: 3
Classifier: Programming Language :: Python :: 3.9
Classifier: Programming Language :: Python :: 3.10
Classifier: Programming Language :: Python :: 3.11
Classifier: Programming Language :: Python :: 3.12
Classifier: Topic :: Software Development :: Libraries
Classifier: Topic :: Software Development :: Libraries :: Python Modules
Classifier: Topic :: Scientific/Engineering :: Artificial Intelligence
Classifier: Topic :: System :: Networking :: Monitoring
Requires-Python: >=3.8.11,<4
Provides-Extra: cli
Provides-Extra: dev
License-File: LICENSE
